AndroidSdkYuanmaJiexi/README.md
AndroidSdkYuanmaJiexi/__init__.py
AndroidSdkYuanmaJiexi/__main__.py
AndroidSdkYuanmaJiexi/file.epub
AndroidSdkYuanmaJiexi/index.html
AndroidSdkYuanmaJiexi/css/__init__.py
AndroidSdkYuanmaJiexi/css/annotations.css
AndroidSdkYuanmaJiexi/css/main.css
AndroidSdkYuanmaJiexi/css/normalize.css
AndroidSdkYuanmaJiexi/css/popup.css
AndroidSdkYuanmaJiexi/font/__init__.py
AndroidSdkYuanmaJiexi/font/fontello.eot
AndroidSdkYuanmaJiexi/font/fontello.svg
AndroidSdkYuanmaJiexi/font/fontello.ttf
AndroidSdkYuanmaJiexi/font/fontello.woff
AndroidSdkYuanmaJiexi/img/__init__.py
AndroidSdkYuanmaJiexi/img/annotator-glyph-sprite.png
AndroidSdkYuanmaJiexi/img/annotator-icon-sprite.png
AndroidSdkYuanmaJiexi/img/apple-touch-icon.png
AndroidSdkYuanmaJiexi/img/cancelfullscreen.png
AndroidSdkYuanmaJiexi/img/close.png
AndroidSdkYuanmaJiexi/img/fullscreen.png
AndroidSdkYuanmaJiexi/img/loader.gif
AndroidSdkYuanmaJiexi/img/menu-icon.png
AndroidSdkYuanmaJiexi/img/save.png
AndroidSdkYuanmaJiexi/img/saved.png
AndroidSdkYuanmaJiexi/img/settings-s.png
AndroidSdkYuanmaJiexi/img/settings.png
AndroidSdkYuanmaJiexi/img/star.png
AndroidSdkYuanmaJiexi/js/__init__.py
AndroidSdkYuanmaJiexi/js/epub.js
AndroidSdkYuanmaJiexi/js/epub.min.js
AndroidSdkYuanmaJiexi/js/epub.min.map
AndroidSdkYuanmaJiexi/js/hooks.min.js
AndroidSdkYuanmaJiexi/js/hooks.min.map
AndroidSdkYuanmaJiexi/js/reader.js
AndroidSdkYuanmaJiexi/js/reader.js.map
AndroidSdkYuanmaJiexi/js/reader.min.js
AndroidSdkYuanmaJiexi/js/reader.min.map
AndroidSdkYuanmaJiexi/js/hooks/__init__.py
AndroidSdkYuanmaJiexi/js/hooks/extensions/__init__.py
AndroidSdkYuanmaJiexi/js/hooks/extensions/highlight.js
AndroidSdkYuanmaJiexi/js/libs/__init__.py
AndroidSdkYuanmaJiexi/js/libs/jquery.min.js
AndroidSdkYuanmaJiexi/js/libs/localforage.min.js
AndroidSdkYuanmaJiexi/js/libs/screenfull.js
AndroidSdkYuanmaJiexi/js/libs/screenfull.min.js
AndroidSdkYuanmaJiexi/js/libs/zip.min.js
AndroidSdkYuanmaJiexi/js/plugins/__init__.py
android_sdk_yuanma_jiexi-2024.3.3.0.dist-info/METADATA
android_sdk_yuanma_jiexi-2024.3.3.0.dist-info/WHEEL
android_sdk_yuanma_jiexi-2024.3.3.0.dist-info/entry_points.txt
android_sdk_yuanma_jiexi-2024.3.3.0.dist-info/top_level.txt
android_sdk_yuanma_jiexi-2024.3.3.0.dist-info/RECORD
